<?xml version='1.0' encoding='utf-8'?>
<Jobs>
  <ApplicationJob xmlns:xsi="http://www.w3.org/2001/XMLSchema-instance" xmlns:xsd="http://www.w3.org/2001/XMLSchema" Guid="1d3c00bf-8a93-4810-869f-e7f9f0f50ceb">
    <WebsiteUrl />
    <UserAgent />
    <UserNotes />
    <LastFileSize>2784</LastFileSize>
    <LastFileDate>2013-11-18T01:41:02+01:00</LastFileDate>
    <IgnoreFileInformation>false</IgnoreFileInformation>
    <DownloadBeta>Default</DownloadBeta>
    <DownloadDate xsi:nil="true" />
    <CheckForUpdatesOnly>false</CheckForUpdatesOnly>
    <VariableChangeIndicator>version</VariableChangeIndicator>
    <CanBeShared>true</CanBeShared>
    <ShareApplication>false</ShareApplication>
    <ExclusiveDownload>false</ExclusiveDownload>
    <HttpReferer />
    <SetupInstructions />
    <Variables>
      <item>
        <key>
          <string>urlPart</string>
        </key>
        <value>
          <UrlVariable>
            <RegexRightToLeft>false</RegexRightToLeft>
            <VariableType>StartEnd</VariableType>
            <Regex />
            <Url>http://www.fosshub.com/Avidemux.html</Url>
            <Name>urlPart</Name>
          </UrlVariable>
        </value>
      </item>
      <item>
        <key>
          <string>genLinkPart</string>
        </key>
        <value>
          <UrlVariable>
            <RegexRightToLeft>false</RegexRightToLeft>
            <VariableType>RegularExpression</VariableType>
            <Regex>(Avidemux/avidemux_[\d\.]+_win)32\.exe</Regex>
            <Url>http://www.fosshub.com/Avidemux.html</Url>
            <TextualContent />
            <Name>genLinkPart</Name>
          </UrlVariable>
        </value>
      </item>
      <item>
        <key>
          <string>url64</string>
        </key>
        <value>
          <UrlVariable>
            <RegexRightToLeft>false</RegexRightToLeft>
            <VariableType>Textual</VariableType>
            <Regex />
            <TextualContent>{genLinkMorePart}</TextualContent>
            <Name>url64</Name>
          </UrlVariable>
        </value>
      </item>
      <item>
        <key>
          <string>genLinkMorePart</string>
        </key>
        <value>
          <UrlVariable>
            <RegexRightToLeft>false</RegexRightToLeft>
            <VariableType>Textual</VariableType>
            <Regex />
            <TextualContent>http://www.fosshub.com/genLink/{genLinkPart}</TextualContent>
            <Name>genLinkMorePart</Name>
          </UrlVariable>
        </value>
      </item>
      <item>
        <key>
          <string>version</string>
        </key>
        <value>
          <UrlVariable>
            <RegexRightToLeft>false</RegexRightToLeft>
            <VariableType>Textual</VariableType>
            <Regex />
            <TextualContent>{genLinkPart:regex:(?&lt;=_)([\d\.]+)(?=_win):$1}</TextualContent>
            <Name>version</Name>
          </UrlVariable>
        </value>
      </item>
    </Variables>
    <ExecuteCommand />
    <ExecutePreCommand />
    <ExecuteCommandType>Batch</ExecuteCommandType>
    <ExecutePreCommandType>Batch</ExecutePreCommandType>
    <Category />
    <SourceType>FixedUrl</SourceType>
    <PreviousLocation>C:\Chocolatey\_work\logo.png</PreviousLocation>
    <DeletePreviousFile>true</DeletePreviousFile>
    <Enabled>true</Enabled>
    <FileHippoId />
    <LastUpdated>2015-07-12T01:29:49.1205911+02:00</LastUpdated>
    <TargetPath>C:\Chocolatey\_work\</TargetPath>
    <FixedDownloadUrl>http://www.fosshub.com/media/v2/img/logo.png</FixedDownloadUrl>
    <Name>avidemux</Name>
  </ApplicationJob>
</Jobs>