<?xml version='1.0' encoding='utf-8'?>
<Jobs>
  <ApplicationJob xmlns:xsi="http://www.w3.org/2001/XMLSchema-instance" xmlns:xsd="http://www.w3.org/2001/XMLSchema" Guid="9c6f9214-35cd-4aec-808f-8bb38dd5e4de">
    <WebsiteUrl />
    <UserAgent />
    <UserNotes />
    <LastFileSize>38678632</LastFileSize>
    <LastFileDate>2013-06-27T23:42:58.7225745</LastFileDate>
    <IgnoreFileInformation>false</IgnoreFileInformation>
    <DownloadBeta>Default</DownloadBeta>
    <DownloadDate xsi:nil="true" />
    <CheckForUpdatesOnly>false</CheckForUpdatesOnly>
    <VariableChangeIndicator />
    <CanBeShared>true</CanBeShared>
    <ShareApplication>false</ShareApplication>
    <ExclusiveDownload>false</ExclusiveDownload>
    <HttpReferer />
    <SetupInstructions />
    <Variables>
      <item>
        <key>
          <string>version</string>
        </key>
        <value>
          <UrlVariable>
            <RegexRightToLeft>false</RegexRightToLeft>
            <VariableType>StartEnd</VariableType>
            <Regex />
            <Url>http://musescore.org/</Url>
            <StartText>&lt;h5 id="download-button-version"&gt;MuseScore </StartText>
            <EndText>&lt;/h5&gt;</EndText>
            <Name>version</Name>
          </UrlVariable>
        </value>
      </item>
    </Variables>
    <ExecuteCommand />
    <ExecutePreCommand />
    <ExecuteCommandType>Batch</ExecuteCommandType>
    <ExecutePreCommandType>Batch</ExecutePreCommandType>
    <Category />
    <SourceType>FixedUrl</SourceType>
    <PreviousLocation>C:\Chocolatey\_work\MuseScore-1.3.exe</PreviousLocation>
    <DeletePreviousFile>true</DeletePreviousFile>
    <Enabled>true</Enabled>
    <FileHippoId />
    <LastUpdated>2013-06-27T23:42:58.7225745</LastUpdated>
    <TargetPath>C:\Chocolatey\_work\</TargetPath>
    <FixedDownloadUrl>http://ftp.osuosl.org/pub/musescore/releases/MuseScore-{version}/MuseScore-{version}.exe</FixedDownloadUrl>
    <Name>musescore</Name>
  </ApplicationJob>
</Jobs>
